dll_downloader/__init__.py
dll_downloader/application/__init__.py
dll_downloader/application/use_cases/__init__.py
dll_downloader/application/use_cases/download_dll.py
dll_downloader/domain/__init__.py
dll_downloader/domain/entities/__init__.py
dll_downloader/domain/entities/dll_file.py
dll_downloader/domain/repositories/__init__.py
dll_downloader/domain/repositories/dll_repository.py
dll_downloader/domain/services/__init__.py
dll_downloader/domain/services/download_resolver.py
dll_downloader/domain/services/hash_service.py
dll_downloader/domain/services/http_client.py
dll_downloader/domain/services/security_scanner.py
dll_downloader/infrastructure/__init__.py
dll_downloader/infrastructure/base.py
dll_downloader/infrastructure/config/__init__.py
dll_downloader/infrastructure/config/settings.py
dll_downloader/infrastructure/http/__init__.py
dll_downloader/infrastructure/http/dll_files_resolver.py
dll_downloader/infrastructure/http/http_client.py
dll_downloader/infrastructure/persistence/__init__.py
dll_downloader/infrastructure/persistence/file_repository.py
dll_downloader/infrastructure/services/__init__.py
dll_downloader/infrastructure/services/virustotal.py
dll_downloader/interfaces/__init__.py
dll_downloader/interfaces/cli.py
dll_downloader-1.0.0.dist-info/licenses/LICENSE
dll_downloader-1.0.0.dist-info/METADATA
dll_downloader-1.0.0.dist-info/WHEEL
dll_downloader-1.0.0.dist-info/entry_points.txt
dll_downloader-1.0.0.dist-info/top_level.txt
dll_downloader-1.0.0.dist-info/RECORD
