Metadata-Version: 2.4
Name: dll-downloader
Version: 1.0.0
Summary: A Python script to automatically search and download DLL files
Author-email: Marc Rivero Lopez <mriverolopez@gmail.com>
License-Expression: LicenseRef-MIT-Attribution
Project-URL: Homepage, https://github.com/seifreed/DLL-Downloader
Project-URL: Repository, https://github.com/seifreed/DLL-Downloader
Project-URL: Issues, https://github.com/seifreed/DLL-Downloader/issues
Keywords: dll,windows,download,security,virustotal
Classifier: Programming Language :: Python :: 3
Classifier: Programming Language :: Python :: 3 :: Only
Classifier: Operating System :: OS Independent
Requires-Python: >=3.10
License-File: LICENSE
Requires-Dist: requests
Provides-Extra: dev
Requires-Dist: black; extra == "dev"
Requires-Dist: ruff; extra == "dev"
Requires-Dist: mypy; extra == "dev"
Requires-Dist: pytest; extra == "dev"
Requires-Dist: pytest-cov; extra == "dev"
Requires-Dist: build; extra == "dev"
Requires-Dist: twine; extra == "dev"
Requires-Dist: types-requests; extra == "dev"
Requires-Dist: pre-commit; extra == "dev"
Dynamic: license-file
